[
    {
        "id": 1,
        "name": "Polygon 1755482106881",
        "description": "",
        "coordinates": [
            {
                "lat": -7.936265073785858,
                "lng": 112.62619153644884
            },
            {
                "lat": -7.936306249836694,
                "lng": 112.62602389838541
            },
            {
                "lat": -7.936445717074962,
                "lng": 112.62596220757807
            },
            {
                "lat": -7.936480827372386,
                "lng": 112.62604401495302
            }
        ],
        "color": "#FF0000",
        "created_at": "2025-08-18 01:55:06",
        "updated_at": "2025-08-18 01:55:06"
    },
    {
        "id": 2,
        "name": "Polygon 1755482869134",
        "description": "",
        "coordinates": [
            {
                "lat": -7.936291612478352,
                "lng": 112.62667866602312
            },
            {
                "lat": -7.936294933127536,
                "lng": 112.62648152366053
            },
            {
                "lat": -7.9364204536475835,
                "lng": 112.62645671322714
            }
        ],
        "color": "#FF0000",
        "created_at": "2025-08-18 02:07:49",
        "updated_at": "2025-08-18 02:07:49"
    },
    {
        "id": 3,
        "name": "Polygon 1755485006709",
        "description": "",
        "coordinates": [
            {
                "lat": -7.973829545068247,
                "lng": 112.59903645484971
            },
            {
                "lat": -7.973955718166795,
                "lng": 112.59949779480027
            },
            {
                "lat": -7.974651661716291,
                "lng": 112.59931808679627
            },
            {
                "lat": -7.9748827572131935,
                "lng": 112.60064309804963
            }
        ],
        "color": "#FF0000",
        "created_at": "2025-08-18 02:43:26",
        "updated_at": "2025-08-18 02:43:26"
    },
    {
        "id": 4,
        "name": "Polygon 1755486068555",
        "description": "",
        "coordinates": [
            {
                "lat": -7.946014936980727,
                "lng": 112.62015153414745
            },
            {
                "lat": -7.946230109899492,
                "lng": 112.62030576116581
            },
            {
                "lat": -7.946216827623827,
                "lng": 112.62072418577213
            }
        ],
        "color": "#FF0000",
        "created_at": "2025-08-18 03:01:08",
        "updated_at": "2025-08-18 03:01:08"
    },
    {
        "id": 5,
        "name": "Polygon 1755487502242",
        "description": "",
        "coordinates": [
            {
                "lat": -7.944848053333447,
                "lng": 112.62088302291613
            },
            {
                "lat": -7.944907823769874,
                "lng": 112.62097824133616
            },
            {
                "lat": -7.94528238497333,
                "lng": 112.62075695909243
            },
            {
                "lat": -7.945415208013048,
                "lng": 112.62064967073184
            },
            {
                "lat": -7.9456356941640935,
                "lng": 112.62099299348574
            },
            {
                "lat": -7.945752578340714,
                "lng": 112.62088034070712
            }
        ],
        "color": "#FF0000",
        "created_at": "2025-08-18 03:25:02",
        "updated_at": "2025-08-18 03:25:02"
    },
    {
        "id": 6,
        "name": "Polygon 1755488706102",
        "description": "",
        "coordinates": [
            {
                "lat": -7.945715541697206,
                "lng": 112.6201656718493
            },
            {
                "lat": -7.946013064932537,
                "lng": 112.62053581669336
            },
            {
                "lat": -7.9460502553217935,
                "lng": 112.62013884975916
            }
        ],
        "color": "#FF0000",
        "created_at": "2025-08-18 03:45:06",
        "updated_at": "2025-08-18 03:45:06"
    },
    {
        "id": 7,
        "name": "Polygon 1755488750887",
        "description": "",
        "coordinates": [
            {
                "lat": -7.945657371506385,
                "lng": 112.62031403257157
            },
            {
                "lat": -7.946162098367613,
                "lng": 112.62026038839127
            },
            {
                "lat": -7.945859262325345,
                "lng": 112.62059834672715
            }
        ],
        "color": "#FF0000",
        "created_at": "2025-08-18 03:45:50",
        "updated_at": "2025-08-18 03:45:50"
    },
    {
        "id": 8,
        "name": "Polygon 1755489478987",
        "description": "",
        "coordinates": [
            {
                "lat": -7.946310587952228,
                "lng": 112.62070747807032
            },
            {
                "lat": -7.946489898596567,
                "lng": 112.62078123881822
            },
            {
                "lat": -7.946501852636733,
                "lng": 112.62053045227533
            }
        ],
        "color": "#FF0000",
        "created_at": "2025-08-18 03:57:58",
        "updated_at": "2025-08-18 03:57:58"
    },
    {
        "id": 9,
        "name": "Polygon 1755489681381",
        "description": "",
        "coordinates": [
            {
                "lat": -7.947523600425434,
                "lng": 112.62278488777261
            },
            {
                "lat": -7.947656422739909,
                "lng": 112.62305042646508
            },
            {
                "lat": -7.9479486316804415,
                "lng": 112.62288681171518
            },
            {
                "lat": -7.948089423186594,
                "lng": 112.62325695655923
            }
        ],
        "color": "#FF0000",
        "created_at": "2025-08-18 04:01:21",
        "updated_at": "2025-08-18 04:01:21"
    },
    {
        "id": 10,
        "name": "Polygon 1755491876880",
        "description": "",
        "coordinates": [
            {
                "lat": -7.945833299796311,
                "lng": 112.62061773503395
            },
            {
                "lat": -7.94601659533387,
                "lng": 112.62070356572242
            },
            {
                "lat": -7.9460059695078415,
                "lng": 112.6204836245832
            }
        ],
        "color": "#FF0000",
        "created_at": "2025-08-18 04:37:56",
        "updated_at": "2025-08-18 04:37:56"
    },
    {
        "id": 11,
        "name": "Polygon 1755500456760",
        "description": "",
        "coordinates": [
            {
                "lat": -7.966086486881264,
                "lng": 112.60778245057443
            },
            {
                "lat": -7.966187427273082,
                "lng": 112.60813918437341
            },
            {
                "lat": -7.9664158712258315,
                "lng": 112.60808554019312
            },
            {
                "lat": -7.9666018138839645,
                "lng": 112.60829207028726
            }
        ],
        "color": "#FF0000",
        "created_at": "2025-08-18 07:00:56",
        "updated_at": "2025-08-18 07:00:56"
    },
    {
        "id": 12,
        "name": "Polygon 1755501285034",
        "description": "",
        "coordinates": [
            {
                "lat": -7.945686578442371,
                "lng": 112.6202054319404
            },
            {
                "lat": -7.946058482479089,
                "lng": 112.6201678810142
            },
            {
                "lat": -7.946061138935278,
                "lng": 112.62063994980082
            }
        ],
        "color": "#FF0000",
        "created_at": "2025-08-18 07:14:45",
        "updated_at": "2025-08-18 07:14:45"
    },
    {
        "id": 13,
        "name": "Polygon 1755501988851",
        "description": "",
        "coordinates": [
            {
                "lat": -7.945694547818113,
                "lng": 112.62020811414942
            },
            {
                "lat": -7.946023948547014,
                "lng": 112.62006595707163
            },
            {
                "lat": -7.946066451847619,
                "lng": 112.62063458538279
            }
        ],
        "color": "#FF0000",
        "created_at": "2025-08-18 07:26:28",
        "updated_at": "2025-08-18 07:26:28"
    },
    {
        "id": 14,
        "name": "Polygon 1755503320072",
        "description": "",
        "coordinates": [
            {
                "lat": -7.945725386646477,
                "lng": 112.62023535285398
            },
            {
                "lat": -7.945805080389465,
                "lng": 112.62014281664297
            },
            {
                "lat": -7.945896728174758,
                "lng": 112.62025010500356
            },
            {
                "lat": -7.9458090650762045,
                "lng": 112.62039092097685
            }
        ],
        "color": "#FF0000",
        "created_at": "2025-08-18 07:48:40",
        "updated_at": "2025-08-18 07:48:40"
    },
    {
        "id": 15,
        "name": "Polygon 1755503679703",
        "description": "",
        "coordinates": [
            {
                "lat": -7.94327542629435,
                "lng": 112.61575573361736
            },
            {
                "lat": -7.943317929879499,
                "lng": 112.61589520848614
            },
            {
                "lat": -7.943425517059743,
                "lng": 112.61581340111118
            }
        ],
        "color": "#FF0000",
        "created_at": "2025-08-18 07:54:39",
        "updated_at": "2025-08-18 07:54:39"
    },
    {
        "id": 16,
        "name": "Polygon 1755656243323",
        "description": "",
        "coordinates": [
            {
                "lat": -7.9410147606802655,
                "lng": 112.61895312392136
            },
            {
                "lat": -7.9413043178608875,
                "lng": 112.61914356076142
            },
            {
                "lat": -7.941429172728995,
                "lng": 112.6192320736589
            },
            {
                "lat": -7.941527462704852,
                "lng": 112.61914624297043
            },
            {
                "lat": -7.941631065626904,
                "lng": 112.6192132981958
            },
            {
                "lat": -7.941774515783536,
                "lng": 112.61943860375305
            }
        ],
        "color": "#FF0000",
        "created_at": "2025-08-20 02:17:23",
        "updated_at": "2025-08-20 02:17:23"
    },
    {
        "id": 17,
        "name": "Polygon 1755656305079",
        "description": "",
        "coordinates": [
            {
                "lat": -7.9427507425620005,
                "lng": 112.61779913611453
            },
            {
                "lat": -7.942984512524563,
                "lng": 112.61820683188479
            },
            {
                "lat": -7.943250160047754,
                "lng": 112.61863598532717
            },
            {
                "lat": -7.943521120344371,
                "lng": 112.61889884181063
            }
        ],
        "color": "#FF0000",
        "created_at": "2025-08-20 02:18:25",
        "updated_at": "2025-08-20 02:18:25"
    },
    {
        "id": 18,
        "name": "Polygon 1755659386874",
        "description": "",
        "coordinates": [
            {
                "lat": -7.939029054349031,
                "lng": 112.62084376049741
            },
            {
                "lat": -7.939443468400988,
                "lng": 112.62059163285001
            },
            {
                "lat": -7.939698492225191,
                "lng": 112.62084912491544
            },
            {
                "lat": -7.939262826429741,
                "lng": 112.62130510044797
            }
        ],
        "color": "#FF0000",
        "created_at": "2025-08-20 03:09:46",
        "updated_at": "2025-08-20 03:09:46"
    },
    {
        "id": 19,
        "name": "Polygon 1755659594369",
        "description": "",
        "coordinates": [
            {
                "lat": -7.938542863848321,
                "lng": 112.61977390000294
            },
            {
                "lat": -7.938723506136109,
                "lng": 112.61962906071614
            },
            {
                "lat": -7.9390157214335275,
                "lng": 112.61991337487171
            },
            {
                "lat": -7.9391697985066605,
                "lng": 112.62021914669941
            },
            {
                "lat": -7.939021034437009,
                "lng": 112.62036935040425
            }
        ],
        "color": "#FF0000",
        "created_at": "2025-08-20 03:13:14",
        "updated_at": "2025-08-20 03:13:14"
    },
    {
        "id": 20,
        "name": "Polygon 1755660270490",
        "description": "",
        "coordinates": [
            {
                "lat": -7.9317751200964075,
                "lng": 112.61586164762616
            },
            {
                "lat": -7.931897288659176,
                "lng": 112.61574298927542
            },
            {
                "lat": -7.93207793386753,
                "lng": 112.61602193901297
            },
            {
                "lat": -7.93238078006817,
                "lng": 112.61590392181631
            }
        ],
        "color": "#FF0000",
        "created_at": "2025-08-20 03:24:30",
        "updated_at": "2025-08-20 03:24:30"
    },
    {
        "id": 21,
        "name": "Polygon 1755660919864",
        "description": "",
        "coordinates": [
            {
                "lat": -7.937599370904391,
                "lng": 112.61908338860779
            },
            {
                "lat": -7.93817317686163,
                "lng": 112.61913703278809
            },
            {
                "lat": -7.938385697383193,
                "lng": 112.61941598252564
            }
        ],
        "color": "#FF0000",
        "created_at": "2025-08-20 03:35:19",
        "updated_at": "2025-08-20 03:35:19"
    },
    {
        "id": 22,
        "name": "Polygon 1755661123721",
        "description": "",
        "coordinates": [
            {
                "lat": -7.966410519951524,
                "lng": 112.61653631133007
            },
            {
                "lat": -7.966793030475722,
                "lng": 112.6168474475758
            },
            {
                "lat": -7.966963035038443,
                "lng": 112.61731951636241
            }
        ],
        "color": "#FF0000",
        "created_at": "2025-08-20 03:38:43",
        "updated_at": "2025-08-20 03:38:43"
    },
    {
        "id": 23,
        "name": "Polygon 1755662580542",
        "description": "",
        "coordinates": [
            {
                "lat": -7.950876591772635,
                "lng": 112.6240745635824
            },
            {
                "lat": -7.951344122308305,
                "lng": 112.62435351331995
            },
            {
                "lat": -7.951673518502116,
                "lng": 112.62528692205713
            },
            {
                "lat": -7.951801026635147,
                "lng": 112.62569461782739
            }
        ],
        "color": "#FF0000",
        "created_at": "2025-08-20 04:03:00",
        "updated_at": "2025-08-20 04:03:00"
    },
    {
        "id": 24,
        "name": "Polygon 1755662648531",
        "description": "",
        "coordinates": [
            {
                "lat": -7.961048461711185,
                "lng": 112.60009499912626
            },
            {
                "lat": -7.9613565992512525,
                "lng": 112.59999843960172
            },
            {
                "lat": -7.96171786365826,
                "lng": 112.60019155865079
            },
            {
                "lat": -7.961940997397548,
                "lng": 112.60043832188016
            },
            {
                "lat": -7.961813492418546,
                "lng": 112.60063144092923
            }
        ],
        "color": "#FF0000",
        "created_at": "2025-08-20 04:04:08",
        "updated_at": "2025-08-20 04:04:08"
    },
    {
        "id": 25,
        "name": "Polygon 1755663021364",
        "description": "",
        "coordinates": [
            {
                "lat": -7.962790468056256,
                "lng": 112.60053109489364
            },
            {
                "lat": -7.963164505643457,
                "lng": 112.60051404050509
            },
            {
                "lat": -7.96347264159181,
                "lng": 112.60065351537386
            },
            {
                "lat": -7.963355762466279,
                "lng": 112.60090564302126
            },
            {
                "lat": -7.963591865736439,
                "lng": 112.60121677926699
            }
        ],
        "color": "#FF0000",
        "created_at": "2025-08-20 04:10:21",
        "updated_at": "2025-08-20 04:10:21"
    },
    {
        "id": 26,
        "name": "Polygon 1755671855806",
        "description": "",
        "coordinates": [
            {
                "lat": -7.967379764427265,
                "lng": 112.61195238867353
            },
            {
                "lat": -7.968059781279885,
                "lng": 112.61172708311628
            },
            {
                "lat": -7.968261661065524,
                "lng": 112.61168416777204
            },
            {
                "lat": -7.968771672712085,
                "lng": 112.61168416777204
            }
        ],
        "color": "#FF0000",
        "created_at": "2025-08-20 06:37:35",
        "updated_at": "2025-08-20 06:37:35"
    },
    {
        "id": 27,
        "name": "Polygon 1755675364766",
        "description": "",
        "coordinates": [
            {
                "lat": -7.927355309414106,
                "lng": 112.58284974505146
            },
            {
                "lat": -7.927522939411062,
                "lng": 112.58287120272358
            },
            {
                "lat": -7.927821804104298,
                "lng": 112.58283231069287
            },
            {
                "lat": -7.928025954792736,
                "lng": 112.58282871886223
            }
        ],
        "color": "#FF0000",
        "created_at": "2025-08-20 07:36:04",
        "updated_at": "2025-08-20 07:36:04"
    },
    {
        "id": 28,
        "name": "Polygon 1755676777546",
        "description": "",
        "coordinates": [
            {
                "lat": -7.945078190524785,
                "lng": 112.6161055623172
            },
            {
                "lat": -7.945145930314105,
                "lng": 112.61621821509583
            },
            {
                "lat": -7.945300005087405,
                "lng": 112.61616322981102
            }
        ],
        "color": "#FF0000",
        "created_at": "2025-08-20 07:59:37",
        "updated_at": "2025-08-20 07:59:37"
    },
    {
        "id": 29,
        "name": "Polygon 1755785879355",
        "description": "",
        "coordinates": [
            {
                "lat": -7.93196992407995,
                "lng": 112.61564818423008
            },
            {
                "lat": -7.932171821624866,
                "lng": 112.6155248026154
            },
            {
                "lat": -7.932408254150131,
                "lng": 112.61587348978733
            },
            {
                "lat": -7.932503889739717,
                "lng": 112.61581179897999
            },
            {
                "lat": -7.932653228179414,
                "lng": 112.61573339178645
            }
        ],
        "color": "#FF0000",
        "created_at": "2025-08-21 14:17:59",
        "updated_at": "2025-08-21 14:17:59"
    },
    {
        "id": 30,
        "name": "Polygon 1755787131550",
        "description": "",
        "coordinates": [
            {
                "lat": -7.958271962246485,
                "lng": 112.60987101154824
            },
            {
                "lat": -7.95907544744399,
                "lng": 112.60925710201263
            },
            {
                "lat": -7.958775834303656,
                "lng": 112.60977731766886
            },
            {
                "lat": -7.959101449479991,
                "lng": 112.60979470923237
            },
            {
                "lat": -7.959592877954491,
                "lng": 112.60973033621602
            }
        ],
        "color": "#FF0000",
        "created_at": "2025-08-21 14:38:51",
        "updated_at": "2025-08-21 14:38:51"
    },
    {
        "id": 31,
        "name": "Polygon 1755787856957",
        "description": "",
        "coordinates": [
            {
                "lat": -7.969610752469543,
                "lng": 112.61163934502797
            },
            {
                "lat": -7.970110137233851,
                "lng": 112.61154278550343
            },
            {
                "lat": -7.9706838977001,
                "lng": 112.61138185296254
            }
        ],
        "color": "#FF0000",
        "created_at": "2025-08-21 14:50:56",
        "updated_at": "2025-08-21 14:50:56"
    },
    {
        "id": 32,
        "name": "Polygon 1755788088773",
        "description": "",
        "coordinates": [
            {
                "lat": -7.962183443007001,
                "lng": 112.60124373939637
            },
            {
                "lat": -7.962335495929449,
                "lng": 112.60109222062508
            },
            {
                "lat": -7.962186740260025,
                "lng": 112.60092055924812
            },
            {
                "lat": -7.962387174359839,
                "lng": 112.60071582653657
            }
        ],
        "color": "#FF0000",
        "created_at": "2025-08-21 14:54:48",
        "updated_at": "2025-08-21 14:54:48"
    },
    {
        "id": 33,
        "name": "Polygon 1755792150886",
        "description": "",
        "coordinates": [
            {
                "lat": -7.968271966128135,
                "lng": 112.59785231477946
            },
            {
                "lat": -7.968398488052671,
                "lng": 112.59793175131325
            },
            {
                "lat": -7.968418742426782,
                "lng": 112.59780702859406
            }
        ],
        "color": "#FF0000",
        "created_at": "2025-08-21 16:02:30",
        "updated_at": "2025-08-21 16:02:30"
    },
    {
        "id": 34,
        "name": "Polygon 1755826261250",
        "description": "",
        "coordinates": [
            {
                "lat": -7.960473043989783,
                "lng": 112.60661015904482
            },
            {
                "lat": -7.960607987207619,
                "lng": 112.60658601916369
            },
            {
                "lat": -7.9607444467412485,
                "lng": 112.60652201769564
            }
        ],
        "color": "#FF0000",
        "created_at": "2025-08-22 01:31:01",
        "updated_at": "2025-08-22 01:31:01"
    },
    {
        "id": 35,
        "name": "Polygon 1755827578573",
        "description": "",
        "coordinates": [
            {
                "lat": -7.96488489530379,
                "lng": 112.60211860044053
            },
            {
                "lat": -7.965201663037353,
                "lng": 112.60212396485856
            },
            {
                "lat": -7.96550040296187,
                "lng": 112.60202206857547
            }
        ],
        "color": "#FF0000",
        "created_at": "2025-08-22 01:52:58",
        "updated_at": "2025-08-22 01:52:58"
    },
    {
        "id": 36,
        "name": "Polygon 1755827851055",
        "description": "",
        "coordinates": [
            {
                "lat": -7.977305142753935,
                "lng": 112.58936949110418
            },
            {
                "lat": -7.977368887865375,
                "lng": 112.5892763090698
            },
            {
                "lat": -7.977412697414698,
                "lng": 112.58941105205129
            }
        ],
        "color": "#FF0000",
        "created_at": "2025-08-22 01:57:31",
        "updated_at": "2025-08-22 01:57:31"
    },
    {
        "id": 37,
        "name": "Polygon 1755829365074",
        "description": "",
        "coordinates": [
            {
                "lat": -7.956799254031338,
                "lng": 112.60140723064211
            },
            {
                "lat": -7.956995826595999,
                "lng": 112.60142198279169
            },
            {
                "lat": -7.957228525904775,
                "lng": 112.60147294476297
            }
        ],
        "color": "#FF0000",
        "created_at": "2025-08-22 02:22:45",
        "updated_at": "2025-08-22 02:22:45"
    },
    {
        "id": 38,
        "name": "Polygon 1755835198934",
        "description": "",
        "coordinates": [
            {
                "lat": -7.935874002182812,
                "lng": 112.62153541589916
            },
            {
                "lat": -7.9361502803851005,
                "lng": 112.62151395822704
            },
            {
                "lat": -7.936511566984821,
                "lng": 112.62154882694423
            }
        ],
        "color": "#FF0000",
        "created_at": "2025-08-22 03:59:59",
        "updated_at": "2025-08-22 03:59:59"
    },
    {
        "id": 39,
        "name": "Polygon 1755847129332",
        "description": "",
        "coordinates": [
            {
                "lat": -7.965948472735419,
                "lng": 112.60347658322691
            },
            {
                "lat": -7.9660480849979285,
                "lng": 112.60346116052507
            },
            {
                "lat": -7.966158328888679,
                "lng": 112.60342526694873
            }
        ],
        "color": "#FF0000",
        "created_at": "2025-08-22 07:18:49",
        "updated_at": "2025-08-22 07:18:49"
    }
]